[
 {
  "n": 0,
  "champion": {
   "Brazil": 0.2669,
   "Netherlands": 0.0912,
   "France": 0.0651,
   "Argentina": 0.218,
   "Belgium": 0.0535,
   "Switzerland": 0.0091,
   "Portugal": 0.0558,
   "England": 0.0225,
   "Spain": 0.0859,
   "Denmark": 0.0436,
   "Germany": 0.0287,
   "Poland": 0.0025,
   "Uruguay": 0.0188,
   "Croatia": 0.0167,
   "Qatar": 0.0003,
   "Serbia": 0.0081,
   "USA": 0.0016,
   "Ecuador": 0.0057,
   "Mexico": 0.0021,
   "South Korea": 0.0004,
   "Iran": 0.0012,
   "Australia": 0.0002,
   "Japan": 0.0009,
   "Wales": 0.0005,
   "Morocco": 0.0003,
   "Canada": 0.0003,
   "Costa Rica": 0.0002,
   "Senegal": 0.0001
  },
  "info_bits": 0.0,
  "label": "baseline"
 },
 {
  "n": 1,
  "champion": {
   "Spain": 0.0791,
   "Brazil": 0.2653,
   "Belgium": 0.0568,
   "Germany": 0.0309,
   "Argentina": 0.2307,
   "England": 0.02,
   "Switzerland": 0.0086,
   "Netherlands": 0.0861,
   "Uruguay": 0.0183,
   "South Korea": 0.0008,
   "France": 0.068,
   "Croatia": 0.0141,
   "Denmark": 0.0407,
   "Portugal": 0.0547,
   "Ecuador": 0.0076,
   "Mexico": 0.0022,
   "Serbia": 0.0087,
   "Poland": 0.0022,
   "USA": 0.0005,
   "Iran": 0.0018,
   "Australia": 0.0003,
   "Japan": 0.0007,
   "Canada": 0.0003,
   "Morocco": 0.0002,
   "Wales": 0.0013,
   "Senegal": 0.0002,
   "Costa Rica": 0.0002,
   "Tunisia": 0.0001
  },
  "info_bits": 0.0055,
  "kind": "group",
  "label": "Qatar 0-2 Ecuador"
 },
 {
  "n": 2,
  "champion": {
   "Germany": 0.0262,
   "Brazil": 0.2712,
   "Argentina": 0.2253,
   "Spain": 0.0818,
   "Portugal": 0.0493,
   "Croatia": 0.0172,
   "Poland": 0.0027,
   "Uruguay": 0.0187,
   "Denmark": 0.0384,
   "Netherlands": 0.0912,
   "England": 0.0241,
   "France": 0.0676,
   "Ecuador": 0.0066,
   "Switzerland": 0.0089,
   "Belgium": 0.0522,
   "Serbia": 0.0097,
   "Mexico": 0.0023,
   "Morocco": 0.0007,
   "Wales": 0.0013,
   "Costa Rica": 0.0004,
   "USA": 0.0015,
   "Japan": 0.0011,
   "South Korea": 0.0006,
   "Iran": 0.0004,
   "Canada": 0.0003,
   "Qatar": 0.0001,
   "Senegal": 0.0002,
   "Australia": 0.0001,
   "Tunisia": 0.0001
  },
  "info_bits": 0.0066,
  "kind": "group",
  "label": "England 6-2 Iran"
 },
 {
  "n": 3,
  "champion": {
   "Argentina": 0.2144,
   "Netherlands": 0.0979,
   "Germany": 0.0285,
   "Belgium": 0.0542,
   "Brazil": 0.2729,
   "France": 0.0663,
   "Denmark": 0.0413,
   "England": 0.0256,
   "Spain": 0.0803,
   "Portugal": 0.0501,
   "Switzerland": 0.0097,
   "USA": 0.0009,
   "Croatia": 0.0138,
   "Ecuador": 0.0071,
   "Mexico": 0.0025,
   "South Korea": 0.0008,
   "Uruguay": 0.0197,
   "Iran": 0.0011,
   "Serbia": 0.0077,
   "Morocco": 0.0004,
   "Poland": 0.0018,
   "Wales": 0.0014,
   "Japan": 0.0007,
   "Qatar": 0.0001,
   "Canada": 0.0005,
   "Australia": 0.0001,
   "Costa Rica": 0.0002,
   "Tunisia": 0.0002,
   "Senegal": 0.0001
  },
  "info_bits": 0.0038,
  "kind": "group",
  "label": "Senegal 0-2 Netherlands"
 },
 {
  "n": 4,
  "champion": {
   "Portugal": 0.0519,
   "Spain": 0.0834,
   "France": 0.0675,
   "Switzerland": 0.0101,
   "Argentina": 0.2273,
   "Serbia": 0.0099,
   "Netherlands": 0.0934,
   "Brazil": 0.2623,
   "Germany": 0.0296,
   "Uruguay": 0.0195,
   "Ecuador": 0.0059,
   "Denmark": 0.0395,
   "Belgium": 0.049,
   "Croatia": 0.0146,
   "England": 0.0253,
   "Wales": 0.0013,
   "Mexico": 0.0029,
   "Japan": 0.0006,
   "Poland": 0.0024,
   "Morocco": 0.0003,
   "Costa Rica": 0.0003,
   "Tunisia": 0.0003,
   "Iran": 0.0008,
   "Canada": 0.0003,
   "Qatar": 0.0001,
   "USA": 0.0008,
   "South Korea": 0.0007,
   "Australia": 0.0002
  },
  "info_bits": 0.003,
  "kind": "group",
  "label": "United States 1-1 Wales"
 },
 {
  "n": 5,
  "champion": {
   "Belgium": 0.054,
   "Brazil": 0.2756,
   "Germany": 0.0284,
   "Spain": 0.084,
   "France": 0.0685,
   "Argentina": 0.1953,
   "Uruguay": 0.0167,
   "Denmark": 0.0437,
   "Netherlands": 0.1013,
   "England": 0.025,
   "Portugal": 0.0527,
   "Serbia": 0.0107,
   "Ecuador": 0.0079,
   "South Korea": 0.0009,
   "Croatia": 0.0168,
   "Switzerland": 0.0095,
   "USA": 0.0016,
   "Wales": 0.001,
   "Morocco": 0.0005,
   "Poland": 0.0017,
   "Iran": 0.0008,
   "Japan": 0.0007,
   "Mexico": 0.0018,
   "Canada": 0.0003,
   "Tunisia": 0.0002,
   "Australia": 0.0003,
   "Saudi Arabia": 0.0001
  },
  "info_bits": 0.0083,
  "kind": "group",
  "label": "Argentina 1-2 Saudi Arabia"
 },
 {
  "n": 6,
  "champion": {
   "France": 0.0701,
   "Brazil": 0.2762,
   "Netherlands": 0.1061,
   "Portugal": 0.0503,
   "Spain": 0.0881,
   "England": 0.0262,
   "Germany": 0.0279,
   "Argentina": 0.1926,
   "Denmark": 0.0354,
   "Uruguay": 0.0203,
   "Croatia": 0.015,
   "Belgium": 0.0547,
   "Poland": 0.0027,
   "Ecuador": 0.0067,
   "Serbia": 0.0081,
   "Mexico": 0.0023,
   "Tunisia": 0.0002,
   "Switzerland": 0.0104,
   "Japan": 0.0009,
   "Australia": 0.0003,
   "Wales": 0.0006,
   "South Korea": 0.0005,
   "Iran": 0.0008,
   "Qatar": 0.0002,
   "Saudi Arabia": 0.0002,
   "USA": 0.002,
   "Canada": 0.0008,
   "Morocco": 0.0003,
   "Costa Rica": 0.0002,
   "Cameroon": 0.0001
  },
  "info_bits": 0.0068,
  "kind": "group",
  "label": "Denmark 0-0 Tunisia"
 },
 {
  "n": 7,
  "champion": {
   "Brazil": 0.2737,
   "Germany": 0.0283,
   "Belgium": 0.055,
   "Denmark": 0.0397,
   "Netherlands": 0.1072,
   "Spain": 0.0855,
   "France": 0.0694,
   "Portugal": 0.0493,
   "Uruguay": 0.0174,
   "Argentina": 0.1952,
   "England": 0.0262,
   "Serbia": 0.0092,
   "Croatia": 0.0166,
   "Ecuador": 0.0058,
   "Poland": 0.0022,
   "Australia": 0.0003,
   "Canada": 0.0005,
   "Switzerland": 0.0097,
   "Mexico": 0.0018,
   "USA": 0.0013,
   "Morocco": 0.0007,
   "Wales": 0.0015,
   "Iran": 0.0008,
   "Tunisia": 0.0003,
   "Japan": 0.0009,
   "Costa Rica": 0.0003,
   "Senegal": 0.0003,
   "South Korea": 0.0008,
   "Saudi Arabia": 0.0003
  },
  "info_bits": 0.0048,
  "kind": "group",
  "label": "Mexico 0-0 Poland"
 },
 {
  "n": 8,
  "champion": {
   "Brazil": 0.2815,
   "Netherlands": 0.103,
   "France": 0.0832,
   "Denmark": 0.0348,
   "Argentina": 0.188,
   "Croatia": 0.0165,
   "Spain": 0.0862,
   "Ecuador": 0.0066,
   "Portugal": 0.05,
   "Belgium": 0.0516,
   "Poland": 0.0026,
   "Germany": 0.0297,
   "Switzerland": 0.0083,
   "Iran": 0.0006,
   "England": 0.0234,
   "Serbia": 0.0086,
   "Uruguay": 0.0177,
   "Tunisia": 0.0003,
   "Mexico": 0.0019,
   "Wales": 0.0017,
   "USA": 0.0009,
   "Japan": 0.0008,
   "Qatar": 0.0001,
   "Senegal": 0.0002,
   "Morocco": 0.0005,
   "Canada": 0.0002,
   "South Korea": 0.0009,
   "Costa Rica": 0.0002,
   "Saudi Arabia": 0.0001
  },
  "info_bits": 0.0049,
  "kind": "group",
  "label": "France 4-1 Australia"
 },
 {
  "n": 9,
  "champion": {
   "England": 0.0248,
   "Belgium": 0.057,
   "Spain": 0.0915,
   "Netherlands": 0.1015,
   "Argentina": 0.1907,
   "Portugal": 0.0519,
   "Uruguay": 0.0187,
   "France": 0.0737,
   "Denmark": 0.038,
   "Brazil": 0.2799,
   "Croatia": 0.0118,
   "USA": 0.0018,
   "Ecuador": 0.0057,
   "Mexico": 0.0013,
   "Germany": 0.0295,
   "Switzerland": 0.008,
   "Canada": 0.0003,
   "Serbia": 0.0077,
   "Iran": 0.0008,
   "Wales": 0.0018,
   "Qatar": 0.0001,
   "Cameroon": 0.0001,
   "Japan": 0.0006,
   "South Korea": 0.0005,
   "Saudi Arabia": 0.0003,
   "Poland": 0.0012,
   "Morocco": 0.0002,
   "Senegal": 0.0002,
   "Australia": 0.0003,
   "Tunisia": 0.0001
  },
  "info_bits": 0.0077,
  "kind": "group",
  "label": "Morocco 0-0 Croatia"
 },
 {
  "n": 10,
  "champion": {
   "Netherlands": 0.1017,
   "Argentina": 0.1928,
   "Uruguay": 0.0207,
   "Portugal": 0.0516,
   "Brazil": 0.2777,
   "France": 0.0811,
   "Belgium": 0.0609,
   "England": 0.0284,
   "Spain": 0.0863,
   "Denmark": 0.0363,
   "Ecuador": 0.0067,
   "Switzerland": 0.01,
   "Germany": 0.0132,
   "Serbia": 0.0095,
   "Croatia": 0.0132,
   "USA": 0.0013,
   "Japan": 0.0023,
   "Poland": 0.0017,
   "Mexico": 0.0011,
   "Wales": 0.001,
   "Iran": 0.0003,
   "Morocco": 0.0004,
   "Canada": 0.0003,
   "Australia": 0.0002,
   "Costa Rica": 0.0006,
   "South Korea": 0.0007,
   "Saudi Arabia": 0.0001
  },
  "info_bits": 0.0193,
  "kind": "group",
  "label": "Germany 1-2 Japan"
 },
 {
  "n": 11,
  "champion": {
   "Brazil": 0.2803,
   "Argentina": 0.1982,
   "France": 0.0778,
   "Spain": 0.0922,
   "Portugal": 0.0565,
   "Belgium": 0.0596,
   "Uruguay": 0.0158,
   "Iran": 0.0011,
   "Netherlands": 0.0973,
   "Switzerland": 0.0101,
   "Denmark": 0.0349,
   "Germany": 0.0138,
   "Ecuador": 0.0053,
   "Serbia": 0.0091,
   "Mexico": 0.0025,
   "Morocco": 0.0007,
   "England": 0.0255,
   "Croatia": 0.0123,
   "Canada": 0.0005,
   "Wales": 0.0013,
   "Japan": 0.0023,
   "South Korea": 0.0005,
   "USA": 0.0009,
   "Tunisia": 0.0003,
   "Poland": 0.001,
   "Costa Rica": 0.0002,
   "Australia": 0.0001,
   "Qatar": 0.0001
  },
  "info_bits": 0.0077,
  "kind": "group",
  "label": "Spain 7-0 Costa Rica"
 },
 {
  "n": 12,
  "champion": {
   "France": 0.0777,
   "Portugal": 0.0544,
   "Argentina": 0.1951,
   "Spain": 0.0876,
   "Brazil": 0.2701,
   "Switzerland": 0.0102,
   "Croatia": 0.0131,
   "England": 0.0248,
   "Netherlands": 0.1092,
   "Denmark": 0.0359,
   "Uruguay": 0.019,
   "Belgium": 0.0659,
   "Germany": 0.0117,
   "Poland": 0.0014,
   "South Korea": 0.0008,
   "Wales": 0.001,
   "Ecuador": 0.0067,
   "Japan": 0.0022,
   "Qatar": 0.0001,
   "Serbia": 0.0083,
   "USA": 0.0012,
   "Morocco": 0.0004,
   "Mexico": 0.0018,
   "Australia": 0.0003,
   "Iran": 0.0004,
   "Tunisia": 0.0002,
   "Saudi Arabia": 0.0003,
   "Canada": 0.0003
  },
  "info_bits": 0.0067,
  "kind": "group",
  "label": "Belgium 1-0 Canada"
 },
 {
  "n": 13,
  "champion": {
   "Netherlands": 0.1036,
   "Brazil": 0.2765,
   "Belgium": 0.0692,
   "Croatia": 0.0142,
   "Argentina": 0.1846,
   "Denmark": 0.036,
   "France": 0.0844,
   "Spain": 0.0898,
   "Portugal": 0.0533,
   "Uruguay": 0.0181,
   "England": 0.024,
   "Ecuador": 0.0075,
   "Iran": 0.0007,
   "Serbia": 0.009,
   "Germany": 0.0109,
   "Switzerland": 0.009,
   "Poland": 0.0014,
   "Mexico": 0.0016,
   "South Korea": 0.0006,
   "USA": 0.0013,
   "Wales": 0.0008,
   "Japan": 0.0022,
   "Canada": 0.0003,
   "Tunisia": 0.0002,
   "Senegal": 0.0001,
   "Morocco": 0.0004,
   "Australia": 0.0001,
   "Saudi Arabia": 0.0002,
   "Costa Rica": 0.0001
  },
  "info_bits": 0.003,
  "kind": "group",
  "label": "Switzerland 1-0 Cameroon"
 },
 {
  "n": 14,
  "champion": {
   "Netherlands": 0.1019,
   "Spain": 0.0878,
   "Brazil": 0.2769,
   "Croatia": 0.0143,
   "Belgium": 0.0678,
   "Argentina": 0.1896,
   "France": 0.076,
   "Denmark": 0.0385,
   "Portugal": 0.0565,
   "Serbia": 0.0103,
   "Switzerland": 0.0094,
   "USA": 0.0013,
   "Uruguay": 0.0151,
   "Germany": 0.0135,
   "England": 0.0242,
   "Morocco": 0.0004,
   "Mexico": 0.0016,
   "Ecuador": 0.0066,
   "Japan": 0.002,
   "Poland": 0.0024,
   "Qatar": 0.0002,
   "Wales": 0.0013,
   "Iran": 0.0008,
   "South Korea": 0.0007,
   "Canada": 0.0004,
   "Tunisia": 0.0005
  },
  "info_bits": 0.0047,
  "kind": "group",
  "label": "Uruguay 0-0 South Korea"
 },
 {
  "n": 15,
  "champion": {
   "Brazil": 0.2797,
   "Netherlands": 0.1014,
   "Portugal": 0.0554,
   "Spain": 0.0874,
   "Argentina": 0.1916,
   "Croatia": 0.0152,
   "Denmark": 0.0367,
   "Belgium": 0.0678,
   "Serbia": 0.0078,
   "France": 0.0785,
   "England": 0.0247,
   "Ecuador": 0.0063,
   "Uruguay": 0.0156,
   "Germany": 0.0118,
   "Poland": 0.002,
   "Japan": 0.0025,
   "Senegal": 0.0002,
   "Switzerland": 0.0093,
   "Iran": 0.001,
   "South Korea": 0.0008,
   "Qatar": 0.0002,
   "Tunisia": 0.0003,
   "Australia": 0.0001,
   "Mexico": 0.0016,
   "USA": 0.0011,
   "Costa Rica": 0.0003,
   "Wales": 0.0007,
   "Morocco": 0.0003,
   "Canada": 0.0001
  },
  "info_bits": 0.0048,
  "kind": "group",
  "label": "Portugal 3-2 Ghana"
 },
 {
  "n": 16,
  "champion": {
   "Denmark": 0.0366,
   "Argentina": 0.1904,
   "England": 0.0243,
   "Netherlands": 0.0956,
   "France": 0.0764,
   "Belgium": 0.0671,
   "Switzerland": 0.0118,
   "Brazil": 0.2879,
   "Spain": 0.0877,
   "Portugal": 0.0545,
   "Croatia": 0.0137,
   "Uruguay": 0.016,
   "Serbia": 0.0083,
   "Germany": 0.0121,
   "Japan": 0.0022,
   "Ecuador": 0.0068,
   "Mexico": 0.0019,
   "Poland": 0.002,
   "Wales": 0.0012,
   "Iran": 0.0005,
   "Canada": 0.0005,
   "USA": 0.0014,
   "South Korea": 0.0004,
   "Qatar": 0.0002,
   "Tunisia": 0.0003,
   "Morocco": 0.0004
  },
  "info_bits": 0.0033,
  "kind": "group",
  "label": "Brazil 2-0 Serbia"
 },
 {
  "n": 17,
  "champion": {
   "Brazil": 0.2838,
   "Argentina": 0.1937,
   "Denmark": 0.0351,
   "Netherlands": 0.1016,
   "Germany": 0.0137,
   "Belgium": 0.0607,
   "USA": 0.0014,
   "France": 0.08,
   "Uruguay": 0.0143,
   "Ecuador": 0.0067,
   "Portugal": 0.0548,
   "Croatia": 0.0129,
   "England": 0.0272,
   "Spain": 0.0896,
   "Switzerland": 0.0102,
   "Japan": 0.0017,
   "Serbia": 0.0057,
   "Poland": 0.0018,
   "Canada": 0.0007,
   "Iran": 0.0018,
   "Mexico": 0.001,
   "South Korea": 0.0008,
   "Saudi Arabia": 0.0002,
   "Wales": 0.0003,
   "Morocco": 0.0003,
   "Australia": 0.0003,
   "Tunisia": 0.0002
  },
  "info_bits": 0.0081,
  "kind": "group",
  "label": "Wales 0-2 Iran"
 },
 {
  "n": 18,
  "champion": {
   "Belgium": 0.0653,
   "Brazil": 0.2898,
   "Argentina": 0.1878,
   "Netherlands": 0.0986,
   "England": 0.0268,
   "Portugal": 0.0551,
   "France": 0.084,
   "Spain": 0.0839,
   "Denmark": 0.0362,
   "Switzerland": 0.0112,
   "Canada": 0.0002,
   "Germany": 0.0113,
   "Serbia": 0.0082,
   "Uruguay": 0.014,
   "Croatia": 0.0135,
   "Ecuador": 0.0057,
   "Mexico": 0.0013,
   "Japan": 0.0018,
   "Australia": 0.0001,
   "Poland": 0.0015,
   "Iran": 0.0018,
   "Morocco": 0.0005,
   "USA": 0.0007,
   "Costa Rica": 0.0001,
   "Wales": 0.0003,
   "South Korea": 0.0002,
   "Senegal": 0.0002,
   "Tunisia": 0.0002,
   "Saudi Arabia": 0.0001
  },
  "info_bits": 0.0051,
  "kind": "group",
  "label": "Qatar 1-3 Senegal"
 },
 {
  "n": 19,
  "champion": {
   "Uruguay": 0.0145,
   "Brazil": 0.2832,
   "Argentina": 0.1926,
   "Spain": 0.0915,
   "Serbia": 0.0059,
   "Denmark": 0.0394,
   "Netherlands": 0.1016,
   "England": 0.02,
   "France": 0.0776,
   "Portugal": 0.0544,
   "Belgium": 0.0672,
   "Germany": 0.0127,
   "Switzerland": 0.0098,
   "Ecuador": 0.0065,
   "Croatia": 0.0127,
   "Australia": 0.0003,
   "Mexico": 0.0013,
   "Iran": 0.0012,
   "USA": 0.0018,
   "Morocco": 0.0006,
   "South Korea": 0.0013,
   "Wales": 0.0003,
   "Poland": 0.0018,
   "Japan": 0.0015,
   "Canada": 0.0004,
   "Costa Rica": 0.0001,
   "Senegal": 0.0001
  },
  "info_bits": 0.008,
  "kind": "group",
  "label": "Netherlands 1-1 Ecuador"
 },
 {
  "n": 20,
  "champion": {
   "Portugal": 0.0544,
   "Argentina": 0.1897,
   "Belgium": 0.0694,
   "Spain": 0.0867,
   "Netherlands": 0.1022,
   "Brazil": 0.2839,
   "Croatia": 0.0123,
   "Uruguay": 0.0149,
   "France": 0.0793,
   "Switzerland": 0.0103,
   "Denmark": 0.0371,
   "England": 0.0232,
   "Iran": 0.0021,
   "Serbia": 0.0054,
   "Tunisia": 0.0005,
   "Mexico": 0.0018,
   "Germany": 0.0097,
   "USA": 0.0018,
   "Poland": 0.0016,
   "Ecuador": 0.0084,
   "Japan": 0.0026,
   "Senegal": 0.0002,
   "Saudi Arabia": 0.0002,
   "Wales": 0.0005,
   "Australia": 0.0003,
   "South Korea": 0.0008,
   "Canada": 0.0005,
   "Morocco": 0.0003
  },
  "info_bits": 0.0082,
  "kind": "group",
  "label": "England 0-0 United States"
 },
 {
  "n": 21,
  "champion": {
   "Denmark": 0.0358,
   "Belgium": 0.0673,
   "Brazil": 0.2906,
   "Uruguay": 0.0154,
   "Argentina": 0.1926,
   "Croatia": 0.0126,
   "France": 0.0766,
   "Spain": 0.0875,
   "Ecuador": 0.0061,
   "Switzerland": 0.0097,
   "Netherlands": 0.1022,
   "Germany": 0.0106,
   "Portugal": 0.0545,
   "Serbia": 0.0077,
   "South Korea": 0.0008,
   "Mexico": 0.0014,
   "Morocco": 0.0008,
   "Canada": 0.0004,
   "England": 0.0192,
   "Japan": 0.0022,
   "Wales": 0.0003,
   "Poland": 0.001,
   "USA": 0.0017,
   "Saudi Arabia": 0.0005,
   "Iran": 0.0019,
   "Australia": 0.0003,
   "Senegal": 0.0002,
   "Costa Rica": 0.0002
  },
  "info_bits": 0.0049,
  "kind": "group",
  "label": "Tunisia 0-1 Australia"
 },
 {
  "n": 22,
  "champion": {
   "Brazil": 0.2903,
   "Denmark": 0.0362,
   "France": 0.076,
   "Croatia": 0.012,
   "Argentina": 0.1869,
   "Uruguay": 0.0153,
   "Netherlands": 0.1027,
   "Spain": 0.0902,
   "Portugal": 0.0556,
   "Belgium": 0.0652,
   "Switzerland": 0.0111,
   "Germany": 0.01,
   "Japan": 0.0015,
   "England": 0.0233,
   "Ecuador": 0.006,
   "Serbia": 0.0069,
   "Morocco": 0.0006,
   "Iran": 0.002,
   "Australia": 0.0004,
   "USA": 0.0018,
   "South Korea": 0.0008,
   "Poland": 0.0026,
   "Mexico": 0.0024,
   "Wales": 0.0001,
   "Costa Rica": 0.0001
  },
  "info_bits": 0.0048,
  "kind": "group",
  "label": "Poland 2-0 Saudi Arabia"
 },
 {
  "n": 23,
  "champion": {
   "Brazil": 0.2925,
   "Spain": 0.0813,
   "Argentina": 0.1895,
   "Denmark": 0.0293,
   "Belgium": 0.0666,
   "Portugal": 0.0552,
   "Netherlands": 0.1011,
   "Serbia": 0.0069,
   "Ecuador": 0.0067,
   "France": 0.0863,
   "Mexico": 0.0024,
   "England": 0.0241,
   "Croatia": 0.0112,
   "Japan": 0.0027,
   "Switzerland": 0.0088,
   "Uruguay": 0.0152,
   "Germany": 0.0129,
   "Iran": 0.0012,
   "USA": 0.0009,
   "Australia": 0.0008,
   "Morocco": 0.0003,
   "South Korea": 0.0006,
   "Wales": 0.0002,
   "Poland": 0.0029,
   "Senegal": 0.0002,
   "Costa Rica": 0.0001,
   "Canada": 0.0001
  },
  "info_bits": 0.007,
  "kind": "group",
  "label": "France 2-1 Denmark"
 },
 {
  "n": 24,
  "champion": {
   "Belgium": 0.0668,
   "Croatia": 0.011,
   "Brazil": 0.2857,
   "Spain": 0.0822,
   "Portugal": 0.0522,
   "Netherlands": 0.092,
   "England": 0.0226,
   "Argentina": 0.2179,
   "France": 0.0869,
   "Serbia": 0.0067,
   "Uruguay": 0.0145,
   "Switzerland": 0.0088,
   "Mexico": 0.001,
   "Poland": 0.0036,
   "Germany": 0.0124,
   "Denmark": 0.0244,
   "South Korea": 0.0009,
   "Japan": 0.0024,
   "Ecuador": 0.0043,
   "Iran": 0.0017,
   "Canada": 0.0007,
   "Morocco": 0.0005,
   "USA": 0.0006,
   "Saudi Arabia": 0.0001,
   "Senegal": 0.0002,
   "Wales": 0.0001
  },
  "info_bits": 0.0094,
  "kind": "group",
  "label": "Argentina 2-0 Mexico"
 },
 {
  "n": 25,
  "champion": {
   "Netherlands": 0.0926,
   "Brazil": 0.273,
   "Argentina": 0.2219,
   "Croatia": 0.0132,
   "Portugal": 0.0495,
   "Belgium": 0.0635,
   "England": 0.0232,
   "Uruguay": 0.0151,
   "France": 0.0853,
   "Denmark": 0.0238,
   "Spain": 0.0875,
   "Switzerland": 0.008,
   "Germany": 0.0205,
   "Serbia": 0.0064,
   "Morocco": 0.0003,
   "Poland": 0.0026,
   "Ecuador": 0.0065,
   "Senegal": 0.0003,
   "South Korea": 0.0008,
   "Japan": 0.0009,
   "Mexico": 0.0009,
   "USA": 0.0014,
   "Iran": 0.0016,
   "Costa Rica": 0.0004,
   "Canada": 0.0003,
   "Cameroon": 0.0001,
   "Wales": 0.0001,
   "Australia": 0.0003
  },
  "info_bits": 0.0132,
  "kind": "group",
  "label": "Japan 0-1 Costa Rica"
 },
 {
  "n": 26,
  "champion": {
   "Brazil": 0.2824,
   "Netherlands": 0.0942,
   "Argentina": 0.216,
   "England": 0.0225,
   "Portugal": 0.0638,
   "Denmark": 0.025,
   "Spain": 0.0843,
   "France": 0.0925,
   "Belgium": 0.0305,
   "Serbia": 0.0086,
   "Germany": 0.0244,
   "Switzerland": 0.0106,
   "South Korea": 0.0014,
   "Croatia": 0.01,
   "Uruguay": 0.0167,
   "Canada": 0.0003,
   "Ecuador": 0.0058,
   "Senegal": 0.0002,
   "Mexico": 0.0016,
   "Morocco": 0.0013,
   "Poland": 0.003,
   "Iran": 0.0013,
   "Japan": 0.0009,
   "USA": 0.0014,
   "Wales": 0.0002,
   "Australia": 0.0003,
   "Costa Rica": 0.0008,
   "Saudi Arabia": 0.0001
  },
  "info_bits": 0.0241,
  "kind": "group",
  "label": "Belgium 0-2 Morocco"
 },
 {
  "n": 27,
  "champion": {
   "Argentina": 0.2128,
   "Netherlands": 0.0998,
   "Brazil": 0.2855,
   "France": 0.0888,
   "Spain": 0.0864,
   "Portugal": 0.0584,
   "Croatia": 0.0157,
   "Uruguay": 0.0138,
   "Denmark": 0.0237,
   "Switzerland": 0.0089,
   "England": 0.0239,
   "Germany": 0.0262,
   "Serbia": 0.0069,
   "Belgium": 0.0317,
   "Morocco": 0.0016,
   "Ecuador": 0.006,
   "Mexico": 0.0011,
   "Iran": 0.0017,
   "Poland": 0.0027,
   "Costa Rica": 0.0008,
   "USA": 0.0015,
   "South Korea": 0.0008,
   "Japan": 0.0011,
   "Senegal": 0.0002,
   "Wales": 0.0001,
   "Tunisia": 0.0001
  },
  "info_bits": 0.0058,
  "kind": "group",
  "label": "Croatia 4-1 Canada"
 },
 {
  "n": 28,
  "champion": {
   "Argentina": 0.2191,
   "Brazil": 0.2804,
   "France": 0.0934,
   "Germany": 0.0251,
   "England": 0.0253,
   "Netherlands": 0.0909,
   "Portugal": 0.0567,
   "Switzerland": 0.0099,
   "Ecuador": 0.0066,
   "Spain": 0.093,
   "Denmark": 0.0209,
   "Uruguay": 0.0158,
   "Belgium": 0.0304,
   "Serbia": 0.0084,
   "Iran": 0.0021,
   "Croatia": 0.0132,
   "Poland": 0.0025,
   "Wales": 0.0002,
   "Mexico": 0.0013,
   "Costa Rica": 0.0005,
   "South Korea": 0.0006,
   "USA": 0.0011,
   "Australia": 0.0002,
   "Morocco": 0.002,
   "Senegal": 0.0002,
   "Japan": 0.0003
  },
  "info_bits": 0.0046,
  "kind": "group",
  "label": "Spain 1-1 Germany"
 },
 {
  "n": 29,
  "champion": {
   "Brazil": 0.2793,
   "Netherlands": 0.0958,
   "Argentina": 0.2126,
   "Portugal": 0.0573,
   "Germany": 0.0248,
   "Denmark": 0.0228,
   "Iran": 0.0018,
   "Spain": 0.0897,
   "Belgium": 0.0307,
   "Ecuador": 0.0067,
   "Serbia": 0.0047,
   "South Korea": 0.0007,
   "France": 0.0932,
   "Morocco": 0.002,
   "Switzerland": 0.0138,
   "England": 0.0266,
   "Uruguay": 0.0145,
   "Saudi Arabia": 0.0002,
   "Croatia": 0.0155,
   "Poland": 0.0031,
   "Costa Rica": 0.0007,
   "USA": 0.001,
   "Wales": 0.0002,
   "Australia": 0.0003,
   "Japan": 0.0008,
   "Senegal": 0.0001,
   "Mexico": 0.0012
  },
  "info_bits": 0.0051,
  "kind": "group",
  "label": "Cameroon 3-3 Serbia"
 },
 {
  "n": 30,
  "champion": {
   "Denmark": 0.0229,
   "Argentina": 0.2197,
   "Brazil": 0.2741,
   "England": 0.0243,
   "Spain": 0.0944,
   "Belgium": 0.0292,
   "Netherlands": 0.0943,
   "Uruguay": 0.0178,
   "France": 0.088,
   "Germany": 0.0243,
   "Switzerland": 0.0132,
   "Croatia": 0.0179,
   "Portugal": 0.0608,
   "Ecuador": 0.0054,
   "Iran": 0.0017,
   "Serbia": 0.0047,
   "Poland": 0.0023,
   "South Korea": 0.0003,
   "Morocco": 0.0012,
   "Costa Rica": 0.0007,
   "Wales": 0.0003,
   "Senegal": 0.0001,
   "Mexico": 0.0013,
   "Australia": 0.0002,
   "Japan": 0.0004,
   "USA": 0.0007
  },
  "info_bits": 0.0032,
  "kind": "group",
  "label": "South Korea 2-3 Ghana"
 },
 {
  "n": 31,
  "champion": {
   "Spain": 0.0871,
   "Brazil": 0.2736,
   "Belgium": 0.0301,
   "Denmark": 0.0213,
   "Netherlands": 0.0917,
   "France": 0.094,
   "Croatia": 0.0148,
   "Argentina": 0.2243,
   "Germany": 0.0257,
   "Portugal": 0.0633,
   "Serbia": 0.0059,
   "Switzerland": 0.0107,
   "England": 0.0243,
   "Uruguay": 0.0185,
   "Ecuador": 0.0054,
   "Poland": 0.0028,
   "Senegal": 0.0001,
   "Morocco": 0.001,
   "Iran": 0.0018,
   "USA": 0.0013,
   "Mexico": 0.0008,
   "Costa Rica": 0.0003,
   "Japan": 0.0006,
   "Australia": 0.0003,
   "Saudi Arabia": 0.0001,
   "Tunisia": 0.0001,
   "South Korea": 0.0001,
   "Wales": 0.0001
  },
  "info_bits": 0.004,
  "kind": "group",
  "label": "Brazil 1-0 Switzerland"
 },
 {
  "n": 32,
  "champion": {
   "Brazil": 0.2817,
   "Belgium": 0.0286,
   "Denmark": 0.0217,
   "Netherlands": 0.0981,
   "Argentina": 0.2127,
   "Germany": 0.0252,
   "Spain": 0.0877,
   "France": 0.0895,
   "USA": 0.0009,
   "England": 0.0242,
   "Portugal": 0.0757,
   "Serbia": 0.0057,
   "Croatia": 0.0141,
   "Switzerland": 0.0096,
   "Poland": 0.003,
   "Uruguay": 0.0097,
   "Wales": 0.0003,
   "Ecuador": 0.0054,
   "Iran": 0.0022,
   "Morocco": 0.0009,
   "South Korea": 0.0002,
   "Mexico": 0.0017,
   "Japan": 0.0003,
   "Australia": 0.0003,
   "Costa Rica": 0.0008,
   "Saudi Arabia": 0.0001
  },
  "info_bits": 0.0082,
  "kind": "group",
  "label": "Portugal 2-0 Uruguay"
 },
 {
  "n": 33,
  "champion": {
   "France": 0.0941,
   "Mexico": 0.0016,
   "Brazil": 0.2856,
   "Argentina": 0.2037,
   "Spain": 0.0873,
   "England": 0.0297,
   "Denmark": 0.0213,
   "Netherlands": 0.0921,
   "Belgium": 0.0295,
   "Portugal": 0.0772,
   "Germany": 0.0286,
   "Switzerland": 0.0101,
   "Croatia": 0.0159,
   "Uruguay": 0.0101,
   "Serbia": 0.0054,
   "Senegal": 0.0005,
   "Poland": 0.0018,
   "Morocco": 0.001,
   "Iran": 0.0018,
   "USA": 0.0013,
   "Costa Rica": 0.0003,
   "Japan": 0.0003,
   "Australia": 0.0003,
   "Wales": 0.0001,
   "Ecuador": 0.0003
  },
  "info_bits": 0.0134,
  "kind": "group",
  "label": "Ecuador 1-2 Senegal"
 },
 {
  "n": 34,
  "champion": {
   "France": 0.1015,
   "Spain": 0.0886,
   "Portugal": 0.0748,
   "Denmark": 0.0182,
   "Brazil": 0.2846,
   "England": 0.0327,
   "Argentina": 0.2004,
   "Netherlands": 0.087,
   "Germany": 0.0272,
   "Uruguay": 0.0113,
   "Switzerland": 0.0111,
   "Belgium": 0.0283,
   "Serbia": 0.0067,
   "Croatia": 0.0152,
   "Senegal": 0.001,
   "Iran": 0.0022,
   "Poland": 0.0037,
   "USA": 0.0009,
   "Morocco": 0.0016,
   "Australia": 0.0004,
   "Costa Rica": 0.0005,
   "Mexico": 0.0013,
   "Japan": 0.0003,
   "Tunisia": 0.0001,
   "Saudi Arabia": 0.0001,
   "South Korea": 0.0002
  },
  "info_bits": 0.0063,
  "kind": "group",
  "label": "Netherlands 2-0 Qatar"
 },
 {
  "n": 35,
  "champion": {
   "Brazil": 0.2873,
   "France": 0.0948,
   "Argentina": 0.2007,
   "Serbia": 0.0063,
   "Netherlands": 0.0927,
   "Denmark": 0.0181,
   "Belgium": 0.0268,
   "Spain": 0.0862,
   "Croatia": 0.0156,
   "Portugal": 0.0782,
   "England": 0.0394,
   "Uruguay": 0.0089,
   "Germany": 0.0232,
   "USA": 0.0008,
   "Switzerland": 0.0116,
   "South Korea": 0.0003,
   "Mexico": 0.0014,
   "Poland": 0.004,
   "Costa Rica": 0.0002,
   "Saudi Arabia": 0.0003,
   "Iran": 0.0012,
   "Morocco": 0.0008,
   "Japan": 0.0003,
   "Australia": 0.0002,
   "Senegal": 0.0008
  },
  "info_bits": 0.0042,
  "kind": "group",
  "label": "Wales 0-3 England"
 },
 {
  "n": 36,
  "champion": {
   "Belgium": 0.0281,
   "Croatia": 0.0137,
   "Brazil": 0.2818,
   "Spain": 0.0877,
   "England": 0.0354,
   "Netherlands": 0.0921,
   "Argentina": 0.2067,
   "France": 0.0976,
   "Serbia": 0.0057,
   "Poland": 0.0037,
   "Denmark": 0.0203,
   "Germany": 0.0278,
   "Portugal": 0.0739,
   "Uruguay": 0.0097,
   "Switzerland": 0.0103,
   "Saudi Arabia": 0.0003,
   "USA": 0.0017,
   "Japan": 0.0004,
   "Mexico": 0.0008,
   "Morocco": 0.0009,
   "Costa Rica": 0.0004,
   "Senegal": 0.0007,
   "Australia": 0.0003,
   "Ghana": 0.0001
  },
  "info_bits": 0.0056,
  "kind": "group",
  "label": "Iran 0-1 United States"
 },
 {
  "n": 37,
  "champion": {
   "Argentina": 0.1968,
   "England": 0.0402,
   "France": 0.0981,
   "Brazil": 0.2853,
   "Portugal": 0.0788,
   "Netherlands": 0.0905,
   "Serbia": 0.0053,
   "Germany": 0.0268,
   "Spain": 0.0823,
   "Uruguay": 0.0102,
   "Belgium": 0.0297,
   "Croatia": 0.0158,
   "Denmark": 0.0193,
   "Switzerland": 0.0107,
   "Senegal": 0.0009,
   "Morocco": 0.0017,
   "Poland": 0.0033,
   "Mexico": 0.0014,
   "Costa Rica": 0.0007,
   "USA": 0.0015,
   "Japan": 0.0003,
   "Australia": 0.0001,
   "Tunisia": 0.0001,
   "Ghana": 0.0001
  },
  "info_bits": 0.0035,
  "kind": "group",
  "label": "Tunisia 1-0 France"
 },
 {
  "n": 38,
  "champion": {
   "Brazil": 0.2787,
   "England": 0.0337,
   "Spain": 0.0907,
   "Argentina": 0.2274,
   "Netherlands": 0.0943,
   "France": 0.0912,
   "Portugal": 0.076,
   "Germany": 0.0252,
   "Croatia": 0.016,
   "Poland": 0.0033,
   "USA": 0.0032,
   "Uruguay": 0.0114,
   "Switzerland": 0.0108,
   "Morocco": 0.0013,
   "Belgium": 0.0283,
   "Australia": 0.0003,
   "South Korea": 0.0003,
   "Serbia": 0.0053,
   "Japan": 0.0003,
   "Mexico": 0.0012,
   "Costa Rica": 0.0003,
   "Senegal": 0.0007,
   "Saudi Arabia": 0.0002
  },
  "info_bits": 0.0381,
  "kind": "group",
  "label": "Australia 1-0 Denmark"
 },
 {
  "n": 39,
  "champion": {
   "France": 0.0978,
   "Portugal": 0.0749,
   "Brazil": 0.2706,
   "Argentina": 0.2528,
   "Netherlands": 0.0815,
   "Spain": 0.0838,
   "Germany": 0.0279,
   "Mexico": 0.001,
   "Belgium": 0.0292,
   "Croatia": 0.0144,
   "Switzerland": 0.0092,
   "Uruguay": 0.0085,
   "England": 0.0369,
   "Japan": 0.0005,
   "Serbia": 0.0043,
   "Australia": 0.0005,
   "Morocco": 0.0013,
   "Poland": 0.0026,
   "Senegal": 0.0005,
   "USA": 0.0011,
   "Costa Rica": 0.0006,
   "South Korea": 0.0001
  },
  "info_bits": 0.008,
  "kind": "group",
  "label": "Poland 0-2 Argentina"
 },
 {
  "n": 40,
  "champion": {
   "Portugal": 0.0774,
   "France": 0.0933,
   "Spain": 0.0809,
   "England": 0.0393,
   "Germany": 0.0281,
   "Argentina": 0.2508,
   "Netherlands": 0.0796,
   "Brazil": 0.2712,
   "Switzerland": 0.0108,
   "Belgium": 0.0298,
   "Poland": 0.0038,
   "Uruguay": 0.009,
   "Croatia": 0.0151,
   "Serbia": 0.006,
   "Morocco": 0.0016,
   "Senegal": 0.0006,
   "USA": 0.0015,
   "Costa Rica": 0.0006,
   "Japan": 0.0003,
   "Australia": 0.0003
  },
  "info_bits": 0.0034,
  "kind": "group",
  "label": "Saudi Arabia 1-2 Mexico"
 },
 {
  "n": 41,
  "champion": {
   "Brazil": 0.2667,
   "France": 0.0973,
   "Portugal": 0.0829,
   "Switzerland": 0.0122,
   "Germany": 0.0343,
   "Argentina": 0.2552,
   "Netherlands": 0.0795,
   "Spain": 0.0778,
   "England": 0.0422,
   "Serbia": 0.0071,
   "USA": 0.0013,
   "Poland": 0.0057,
   "Croatia": 0.0101,
   "Uruguay": 0.0079,
   "Belgium": 0.0159,
   "Senegal": 0.0008,
   "Morocco": 0.0018,
   "Japan": 0.0005,
   "Australia": 0.0005,
   "Costa Rica": 0.0005
  },
  "info_bits": 0.0098,
  "kind": "group",
  "label": "Canada 1-2 Morocco"
 },
 {
  "n": 42,
  "champion": {
   "France": 0.1017,
   "Argentina": 0.2595,
   "Netherlands": 0.0811,
   "Croatia": 0.0119,
   "Brazil": 0.2655,
   "Spain": 0.0779,
   "Germany": 0.0329,
   "Portugal": 0.0911,
   "England": 0.0381,
   "Poland": 0.005,
   "Switzerland": 0.0131,
   "Serbia": 0.0065,
   "Costa Rica": 0.0007,
   "Australia": 0.0008,
   "Uruguay": 0.0092,
   "Morocco": 0.0025,
   "Japan": 0.0004,
   "Senegal": 0.0007,
   "USA": 0.0015
  },
  "info_bits": 0.0249,
  "kind": "group",
  "label": "Croatia 0-0 Belgium"
 },
 {
  "n": 43,
  "champion": {
   "Spain": 0.1128,
   "Brazil": 0.3119,
   "Argentina": 0.2437,
   "Portugal": 0.0694,
   "France": 0.0893,
   "Uruguay": 0.012,
   "England": 0.0349,
   "Netherlands": 0.0796,
   "Switzerland": 0.0102,
   "Croatia": 0.0207,
   "Japan": 0.0013,
   "USA": 0.0021,
   "Serbia": 0.0052,
   "Morocco": 0.0015,
   "Australia": 0.0004,
   "Poland": 0.0043,
   "Senegal": 0.0003,
   "Costa Rica": 0.0002,
   "South Korea": 0.0001
  },
  "info_bits": 0.0766,
  "kind": "group",
  "label": "Japan 2-1 Spain"
 },
 {
  "n": 44,
  "champion": {
   "Argentina": 0.2507,
   "Brazil": 0.2922,
   "Spain": 0.1353,
   "Netherlands": 0.0794,
   "France": 0.0872,
   "Croatia": 0.0211,
   "Portugal": 0.0607,
   "Japan": 0.0014,
   "USA": 0.0021,
   "England": 0.0376,
   "Uruguay": 0.0121,
   "Morocco": 0.0015,
   "Switzerland": 0.009,
   "Senegal": 0.0012,
   "Serbia": 0.0044,
   "Poland": 0.0038,
   "Australia": 0.0003,
   "South Korea": 0.0001
  },
  "info_bits": 0.0065,
  "kind": "group",
  "label": "Costa Rica 2-4 Germany"
 },
 {
  "n": 45,
  "champion": {
   "Netherlands": 0.0841,
   "Argentina": 0.2522,
   "Brazil": 0.29,
   "Spain": 0.1308,
   "France": 0.0868,
   "England": 0.0326,
   "Uruguay": 0.0153,
   "Portugal": 0.0658,
   "Serbia": 0.0045,
   "Croatia": 0.0198,
   "Switzerland": 0.0088,
   "Poland": 0.0041,
   "Senegal": 0.0006,
   "USA": 0.0014,
   "Japan": 0.0016,
   "Morocco": 0.001,
   "South Korea": 0.0001,
   "Australia": 0.0007
  },
  "info_bits": 0.0027,
  "kind": "group",
  "label": "Ghana 0-2 Uruguay"
 },
 {
  "n": 46,
  "champion": {
   "Brazil": 0.3227,
   "Argentina": 0.2424,
   "Netherlands": 0.0844,
   "France": 0.0801,
   "Croatia": 0.0202,
   "Spain": 0.1278,
   "Portugal": 0.0664,
   "Switzerland": 0.0073,
   "England": 0.0333,
   "Morocco": 0.0018,
   "Serbia": 0.0043,
   "Poland": 0.0046,
   "Japan": 0.002,
   "South Korea": 0.0015,
   "USA": 0.0011,
   "Senegal": 0.0001
  },
  "info_bits": 0.0318,
  "kind": "group",
  "label": "South Korea 2-1 Portugal"
 },
 {
  "n": 47,
  "champion": {
   "Brazil": 0.3188,
   "Argentina": 0.2488,
   "Netherlands": 0.0798,
   "Portugal": 0.0738,
   "Croatia": 0.0204,
   "Spain": 0.1217,
   "England": 0.0324,
   "France": 0.0863,
   "Switzerland": 0.0059,
   "Serbia": 0.0017,
   "South Korea": 0.0014,
   "Poland": 0.0037,
   "Japan": 0.0013,
   "USA": 0.0018,
   "Senegal": 0.0004,
   "Morocco": 0.0011,
   "Australia": 0.0004,
   "Cameroon": 0.0001
  },
  "info_bits": 0.008,
  "kind": "group",
  "label": "Cameroon 1-0 Brazil"
 },
 {
  "n": 48,
  "champion": {
   "Brazil": 0.3298,
   "Argentina": 0.2425,
   "Spain": 0.125,
   "Portugal": 0.065,
   "England": 0.0336,
   "Switzerland": 0.012,
   "Croatia": 0.0207,
   "Netherlands": 0.0781,
   "France": 0.0843,
   "South Korea": 0.0016,
   "USA": 0.0011,
   "Morocco": 0.0011,
   "Poland": 0.0037,
   "Senegal": 0.0003,
   "Japan": 0.0011,
   "Australia": 0.0003
  },
  "info_bits": 0.0077,
  "kind": "group",
  "label": "Serbia 2-3 Switzerland"
 },
 {
  "n": 49,
  "champion": {
   "Brazil": 0.3258,
   "Switzerland": 0.0138,
   "Argentina": 0.2253,
   "Netherlands": 0.1001,
   "Portugal": 0.0606,
   "Spain": 0.1267,
   "Poland": 0.0039,
   "England": 0.0347,
   "France": 0.0844,
   "Croatia": 0.0195,
   "Morocco": 0.0016,
   "Japan": 0.0017,
   "South Korea": 0.0011,
   "Senegal": 0.0005,
   "Australia": 0.0005
  },
  "info_bits": 0.0078,
  "kind": "ko",
  "label": "Netherlands 3-1 United States"
 },
 {
  "n": 50,
  "champion": {
   "Portugal": 0.0609,
   "Spain": 0.1332,
   "France": 0.0892,
   "Brazil": 0.3113,
   "Argentina": 0.2462,
   "Netherlands": 0.0871,
   "Croatia": 0.0184,
   "Switzerland": 0.013,
   "England": 0.0311,
   "Poland": 0.0043,
   "Japan": 0.0014,
   "South Korea": 0.0016,
   "Morocco": 0.0016,
   "Senegal": 0.0007
  },
  "info_bits": 0.0048,
  "kind": "ko",
  "label": "Argentina 2-1 Australia"
 },
 {
  "n": 51,
  "champion": {
   "Portugal": 0.0602,
   "Brazil": 0.3123,
   "Spain": 0.1258,
   "Argentina": 0.2432,
   "Croatia": 0.0177,
   "Switzerland": 0.0127,
   "France": 0.1117,
   "England": 0.0283,
   "Netherlands": 0.0856,
   "South Korea": 0.0008,
   "Morocco": 0.0008,
   "Japan": 0.001
  },
  "info_bits": 0.0123,
  "kind": "ko",
  "label": "France 3-1 Poland"
 },
 {
  "n": 52,
  "champion": {
   "Spain": 0.1187,
   "Argentina": 0.252,
   "Brazil": 0.3241,
   "France": 0.0995,
   "England": 0.0333,
   "Netherlands": 0.0833,
   "Switzerland": 0.0118,
   "Croatia": 0.0182,
   "Portugal": 0.0557,
   "South Korea": 0.0011,
   "Morocco": 0.0013,
   "Japan": 0.0013
  },
  "info_bits": 0.003,
  "kind": "ko",
  "label": "England 3-0 Senegal"
 },
 {
  "n": 53,
  "champion": {
   "Argentina": 0.2535,
   "Spain": 0.1174,
   "Brazil": 0.3018,
   "France": 0.1095,
   "Portugal": 0.0565,
   "Netherlands": 0.0843,
   "Switzerland": 0.0113,
   "England": 0.0366,
   "Croatia": 0.027,
   "South Korea": 0.0009,
   "Morocco": 0.0011
  },
  "info_bits": 0.0066,
  "kind": "ko",
  "label": "Japan 1-1 Croatia"
 },
 {
  "n": 54,
  "champion": {
   "Portugal": 0.0583,
   "France": 0.1008,
   "Spain": 0.1141,
   "Brazil": 0.3423,
   "Argentina": 0.2401,
   "England": 0.0357,
   "Netherlands": 0.0771,
   "Switzerland": 0.0112,
   "Croatia": 0.0191,
   "Morocco": 0.0014
  },
  "info_bits": 0.0086,
  "kind": "ko",
  "label": "Brazil 4-1 South Korea"
 },
 {
  "n": 55,
  "champion": {
   "Argentina": 0.2489,
   "Brazil": 0.3538,
   "Netherlands": 0.0889,
   "Portugal": 0.0919,
   "France": 0.1205,
   "Switzerland": 0.0203,
   "England": 0.0442,
   "Croatia": 0.0248,
   "Morocco": 0.0066
  },
  "info_bits": 0.1948,
  "kind": "ko",
  "label": "Morocco 0-0 Spain"
 },
 {
  "n": 56,
  "champion": {
   "France": 0.1125,
   "Brazil": 0.3499,
   "Portugal": 0.1462,
   "Argentina": 0.2418,
   "England": 0.0415,
   "Croatia": 0.0209,
   "Netherlands": 0.0818,
   "Morocco": 0.0053
  },
  "info_bits": 0.0507,
  "kind": "ko",
  "label": "Portugal 6-1 Switzerland"
 },
 {
  "n": 57,
  "champion": {
   "Croatia": 0.1119,
   "Portugal": 0.1835,
   "France": 0.1474,
   "Argentina": 0.3586,
   "Netherlands": 0.1376,
   "England": 0.0536,
   "Morocco": 0.0074
  },
  "info_bits": 0.7187,
  "kind": "ko",
  "label": "Croatia 1-1 Brazil"
 },
 {
  "n": 58,
  "champion": {
   "Argentina": 0.5541,
   "France": 0.1335,
   "Croatia": 0.097,
   "Portugal": 0.163,
   "England": 0.0467,
   "Morocco": 0.0057
  },
  "info_bits": 0.2695,
  "kind": "ko",
  "label": "Netherlands 2-2 Argentina"
 },
 {
  "n": 59,
  "champion": {
   "England": 0.0774,
   "Argentina": 0.6002,
   "France": 0.1876,
   "Morocco": 0.0326,
   "Croatia": 0.1022
  },
  "info_bits": 0.3075,
  "kind": "ko",
  "label": "Morocco 1-0 Portugal"
 },
 {
  "n": 60,
  "champion": {
   "Argentina": 0.5766,
   "Croatia": 0.1007,
   "France": 0.2972,
   "Morocco": 0.0256
  },
  "info_bits": 0.1527,
  "kind": "ko",
  "label": "England 1-2 France"
 },
 {
  "n": 61,
  "champion": {
   "Argentina": 0.7338,
   "France": 0.2468,
   "Morocco": 0.0193
  },
  "info_bits": 0.1814,
  "kind": "ko",
  "label": "Argentina 3-0 Croatia"
 },
 {
  "n": 62,
  "champion": {
   "Argentina": 0.6998,
   "France": 0.3002
  },
  "info_bits": 0.0368,
  "kind": "ko",
  "label": "France 2-0 Morocco"
 },
 {
  "n": 63,
  "champion": {
   "Argentina": 0.6998,
   "France": 0.3002
  },
  "info_bits": 0.0,
  "kind": "group",
  "label": "Croatia 2-1 Morocco"
 },
 {
  "n": 64,
  "champion": {
   "Argentina": 1.0
  },
  "info_bits": 0.5149,
  "kind": "ko",
  "label": "Argentina 3-3 France"
 }
]